aedev/app_tpls/__init__.py
aedev/app_tpls/templates/de_tpl_main.py
aedev/app_tpls/templates/main.kv
aedev/app_tpls/templates/requirements.txt
aedev/app_tpls/templates/de_mtp_ae_updater_moves/FStringEvalSuggestions.txt
aedev/app_tpls/templates/de_mtp_ae_updater_moves/{project_name}.ini
aedev/app_tpls/templates/de_mtp_img/access_right_C.png
aedev/app_tpls/templates/de_mtp_img/access_right_D.png
aedev/app_tpls/templates/de_mtp_img/access_right_U.png
aedev/app_tpls/templates/de_mtp_img/access_right_r.png
aedev/app_tpls/templates/de_mtp_img/access_right_x.png
aedev/app_tpls/templates/de_mtp_img/app_icon.jpg
aedev/app_tpls/templates/de_mtp_img/app_icon.png
aedev/app_tpls/templates/de_mtp_img/open_userz_access.png
aedev/app_tpls/templates/de_mtp_img/light_1/access_right_C.png
aedev/app_tpls/templates/de_mtp_img/light_1/access_right_D.png
aedev/app_tpls/templates/de_mtp_img/light_1/access_right_U.png
aedev/app_tpls/templates/de_mtp_img/light_1/access_right_r.png
aedev/app_tpls/templates/de_mtp_img/light_1/access_right_x.png
aedev/app_tpls/templates/de_mtp_img/light_1/app_icon.png
aedev/app_tpls/templates/de_mtp_img/light_1/open_userz_access.png
aedev/app_tpls/templates/de_mtp_loc/de/Msg.txt
aedev/app_tpls/templates/de_mtp_loc/en/Msg.txt
aedev/app_tpls/templates/de_mtp_loc/es/Msg.txt
aedev/app_tpls/templates/de_mtp_snd/filter_off.wav
aedev/app_tpls/templates/de_mtp_snd/filter_on.wav
aedev_app_tpls-0.3.18.dist-info/licenses/LICENSE.md
aedev_app_tpls-0.3.18.dist-info/METADATA
aedev_app_tpls-0.3.18.dist-info/WHEEL
aedev_app_tpls-0.3.18.dist-info/top_level.txt
aedev_app_tpls-0.3.18.dist-info/RECORD
